{
  "display": {
    "icon": {
      "id": "minecraft:red_bed"
    },
    "title": "Home Sweet Home",
    "description": "Make your house a home with a bed",
    "frame": "goal"
  },
  "parent": "antfarm:glass",
  "criteria": {
    "craft_bed": {
      "trigger": "minecraft:recipe_crafted",
      "conditions": {
        "recipe_id": "minecraft:white_bed"
      }
    },
    "use_bed": {
      "trigger": "minecraft:slept_in_bed",
      "conditions": {}
    }
  },
  "requirements": [
    [
      "craft_bed",
      "use_bed"
    ]
  ]
}
